CityTime-1.0.0.dist-info/LICENSE.txt
CityTime-1.0.0.dist-info/METADATA
CityTime-1.0.0.dist-info/RECORD
CityTime-1.0.0.dist-info/WHEEL
CityTime-1.0.0.dist-info/top_level.txt
citytime/__init__.py
citytime/citytime.py
