Metadata-Version: 2.1
Name: CityTime
Version: 1.0.0
Summary: A tool for comparing time between different locations/timezones
Home-page: https://github.com/tweyter/CityTime
Author: Thorsten Weyter
Author-email: tweyter@gmail.com
Maintainer: Thorsten Weyter
Maintainer-email: tweyter@gmail.com
License: MIT
Keywords: time datetime olson timezone
Platform: UNKNOWN
Classifier: Development Status :: 5 - Production/Stable
Classifier: Intended Audience :: Developers
Classifier: Natural Language :: English
Classifier: License :: OSI Approved :: MIT License
Classifier: Operating System :: OS Independent
Classifier: Programming Language :: Python
Classifier: Programming Language :: Python :: 3.5
Classifier: Programming Language :: Python :: 3.6
Classifier: Topic :: Utilities
Requires-Dist: pytz
